{
  "id": "103376",
  "mergedIDs": null,
  "timestamp": "2014-05-31 06:57:26",
  "name": "Barbara Thaden",
  "surname": "Thaden",
  "nationality": "FR",
  "nationality fr": "France",
  "birth location": "Châteaubriant  (FR)",
  "birth day": 1,
  "birth month": 1,
  "birth year": "1960",
  "death location": null,
  "death day": null,
  "death month": null,
  "death year": null,
  "attributes": "Female",
  "media": null,
  "r00": "24851",
  "r01": "27303",
  "r02": "24845",
  "r03": "25951",
  "r04": "22628",
  "r05": "22013",
  "r06": "48886",
  "r07": "53232",
  "r08": "81513",
  "awards": null,
  "website": null,
  "all-shows-first": "1990",
  "all-shows-total": "14",
  "2005-shows-biennials": "4",
  "2005-shows-galleries": "4",
  "2005-shows-museums": "4",
  "2005-countries-total": "France (7), Germany (3)",
  "2005-shows-with": "Barbara Thaden (6)",
  "representing-galleries": null,
  "collecting-museums": "FRAC Poitou-Charentes - Angoulême (63 Boulevard Besson Bey, 16000 Angoulême, France)",
  "first_name": "Barbara",
  "last_name": "Thaden",
  "genre": "f",
  "birthDate": "1960-01-01",
  "age": 54,
  "age_range": "41-60",
  "expos": {
    "2007": [
      {
        "i": "103376-8441-2007-08-01",
        "c": "DE",
        "n": "Kunstportale",
        "t": "Autre",
        "st": "Group",
        "ct": "Berlin",
        "o": "Galerie Nord | Kunstverein Tiergarten",
        "d": [
          "2007-08-01",
          "2007-09-01"
        ]
      }
    ],
    "2008": [
      {
        "i": "103376-29578-2008-06-01",
        "c": "DE",
        "n": "Eingefädelt",
        "t": "Autre",
        "st": "Group",
        "ct": "Cologne",
        "o": "Museum Zündorfer Wehrturm",
        "d": [
          "2008-06-01",
          "2008-06-22"
        ]
      },
      {
        "i": "103376-21676-2008-09-04",
        "c": "DE",
        "n": "Barbara Thaden - Treppppen",
        "t": "Institution publique",
        "st": "Solo",
        "ct": "Cologne",
        "o": "GALERIE IM TURM",
        "d": [
          "2008-09-04",
          "2008-09-25"
        ]
      }
    ],
    "2009": [
      {
        "i": "103376-1293-2009-05-29",
        "c": "FR"
      },
      {
        "i": "103376-1293-2009-05-29",
        "c": "FR"
      },
      {
        "i": "103376-11880-2009-05-14",
        "c": "FR"
      },
      {
        "i": "103376-11880-2009-05-14",
        "c": "FR"
      }
    ],
    "2012": [
      {
        "i": "103376-11880-2012-01-16",
        "c": "FR"
      },
      {
        "i": "103376-11880-2012-01-16",
        "c": "FR"
      },
      {
        "i": "103376-27836-2012-10-26",
        "c": "FR"
      },
      {
        "i": "103376-27836-2012-10-26",
        "c": "FR"
      },
      {
        "i": "103376-11880-2012-05-19",
        "c": "FR"
      },
      {
        "i": "103376-11880-2012-05-19",
        "c": "FR"
      }
    ],
    "2013": [
      {
        "i": "103376-30303-2013-07-05",
        "c": "FR"
      },
      {
        "i": "103376-30303-2013-07-05",
        "c": "FR"
      }
    ],
    "2014": [
      {
        "i": "103376-13471-2014-04-12",
        "c": "DE",
        "n": "Single Moms",
        "t": "Institution publique",
        "st": "Group",
        "ct": "Bonn",
        "o": "Frauenmuseum Bonn",
        "d": [
          "2014-04-12",
          "2014-11-11"
        ],
        "a": "103376",
        "an": "Barbara Thaden"
      }
    ],
    "today": [
      {
        "i": "103376",
        "c": "DE",
        "g": "f",
        "a": "41-60"
      },
      {
        "i": "103376-13471-2014-04-12",
        "c": "DE",
        "n": "Single Moms",
        "t": "Institution publique",
        "st": "Group",
        "ct": "Bonn",
        "o": "Frauenmuseum Bonn",
        "d": [
          "2014-04-12",
          "2014-11-11"
        ],
        "a": "103376",
        "an": "Barbara Thaden"
      }
    ],
    "2010": [
      {
        "i": "103376-11880-2010-09-16",
        "c": "FR"
      },
      {
        "i": "103376-11880-2010-09-16",
        "c": "FR"
      }
    ]
  }
}