{
  "id": "126815",
  "mergedIDs": null,
  "timestamp": "2014-02-22 06:55:01",
  "name": "Lin Delpierre",
  "surname": "Delpierre",
  "nationality": "FR",
  "nationality fr": "France",
  "birth location": "Bayonne (FR)",
  "birth day": 1,
  "birth month": 1,
  "birth year": "1962",
  "death location": null,
  "death day": null,
  "death month": null,
  "death year": null,
  "attributes": null,
  "media": null,
  "r00": "66959",
  "r01": "62319",
  "r02": "56503",
  "r03": "64227",
  "r04": "56910",
  "r05": "52583",
  "r06": "45192",
  "r07": "38436",
  "r08": "36933",
  "awards": null,
  "website": null,
  "all-shows-first": "1993",
  "all-shows-total": "9",
  "2005-shows-biennials": "2",
  "2005-shows-galleries": "2",
  "2005-shows-museums": null,
  "2005-countries-total": "France (2)",
  "2005-shows-with": null,
  "representing-galleries": null,
  "collecting-museums": "49 NORD 6 EST – Frac Lorraine (Rue des Trinitaires 1 bis, 57000 Metz, France)",
  "first_name": "Lin",
  "last_name": "Delpierre",
  "genre": "c",
  "birthDate": "1962-01-01",
  "age": 52,
  "age_range": "46-55",
  "expos": {
  }
}