{
  "id": "217410",
  "mergedIDs": null,
  "timestamp": "2014-05-24 07:30:58",
  "name": "Steven Le Priol",
  "surname": "Le Priol",
  "nationality": "FR",
  "nationality fr": "France",
  "birth location": "Vannes (FR)",
  "birth day": 1,
  "birth month": 1,
  "birth year": "1972",
  "death location": null,
  "death day": null,
  "death month": null,
  "death year": null,
  "attributes": "Male",
  "media": null,
  "r00": "57407",
  "r01": "57106",
  "r02": "55059",
  "r03": "49802",
  "r04": "65419",
  "r05": "58588",
  "r06": "56474",
  "r07": "73699",
  "r08": null,
  "awards": null,
  "website": null,
  "all-shows-first": "2007",
  "all-shows-total": "7",
  "2005-shows-biennials": "6",
  "2005-shows-galleries": "6",
  "2005-shows-museums": null,
  "2005-countries-total": "France (4), Iceland (1), United Kingdom (1)",
  "2005-shows-with": "Steven Le Priol (4), Niklas Goldbach (2), Julio Rondo (2), Miguel Rothschild (2)",
  "representing-galleries": "Bendana-Pinel | Art Contemporain (4, Rue du Perche, 75003 Paris, France)",
  "collecting-museums": null,
  "first_name": "Steven",
  "last_name": "Le",
  "genre": "m",
  "birthDate": "1972-01-01",
  "age": 42,
  "age_range": "41-60",
  "expos": {
    "2007": [
      {
        "i": "217410-20542-2007-01-12",
        "c": "FR"
      },
      {
        "i": "217410-20542-2007-01-12",
        "c": "FR"
      }
    ],
    "2009": [
      {
        "i": "217410-19747-2009-03-14",
        "c": "FR"
      },
      {
        "i": "217410-19747-2009-03-14",
        "c": "FR"
      },
      {
        "i": "217410-13758-2009-08-08",
        "c": "IS",
        "n": "Fyrirheitna landið",
        "t": "Galerie privée",
        "st": "Group",
        "ct": "Akureyri",
        "o": "galleriBOX",
        "d": [
          "2009-08-08",
          "2009-08-23"
        ]
      }
    ],
    "2011": [
      {
        "i": "217410-10737-2011-07-08",
        "c": "GB",
        "n": "The pavement and the beach",
        "t": "Galerie privée",
        "st": "Group",
        "ct": "London",
        "o": "Paradise Row",
        "d": [
          "2011-07-08",
          "2011-04-13"
        ]
      },
      {
        "i": "217410-19747-2011-01-08",
        "c": "FR"
      },
      {
        "i": "217410-19747-2011-01-08",
        "c": "FR"
      }
    ],
    "2013": [
      {
        "i": "217410-19747-2013-03-16",
        "c": "FR"
      },
      {
        "i": "217410-19747-2013-03-16",
        "c": "FR"
      }
    ],
    "2008": [
      {
        "i": "217410-19747-2008-06-26",
        "c": "FR"
      },
      {
        "i": "217410-19747-2008-06-26",
        "c": "FR"
      }
    ]
  }
}