{
  "id": "9610",
  "mergedIDs": null,
  "timestamp": "2014-05-24 06:18:45",
  "name": "Jean François Chaussepied",
  "surname": "Chaussepied",
  "nationality": "FR",
  "nationality fr": "France",
  "birth location": "Quimper (FR)",
  "birth day": 1,
  "birth month": 1,
  "birth year": "1944",
  "death location": null,
  "death day": null,
  "death month": null,
  "death year": null,
  "attributes": "Male",
  "media": null,
  "r00": "66847",
  "r01": "64731",
  "r02": "58995",
  "r03": "52777",
  "r04": "61693",
  "r05": "52573",
  "r06": "43904",
  "r07": "48102",
  "r08": "38527",
  "awards": null,
  "website": null,
  "all-shows-first": "1996",
  "all-shows-total": "8",
  "2005-shows-biennials": "3",
  "2005-shows-galleries": "3",
  "2005-shows-museums": null,
  "2005-countries-total": "Germany (3)",
  "2005-shows-with": null,
  "representing-galleries": "Galerie Sievi (Gneisenaustr. 112, 10961 Berlin, Germany)",
  "collecting-museums": null,
  "first_name": "Jean",
  "last_name": "François",
  "genre": "m",
  "birthDate": "1944-01-01",
  "age": 70,
  "age_range": "61-100",
  "expos": {
    "2010": [
      {
        "i": "9610-651-2010-05-08",
        "c": "DE",
        "n": "20 Jahre Galerie Sievi – Zeitzeugen der Kunst in Kreuzberg",
        "t": "Galerie privée",
        "st": "Group",
        "ct": "Berlin",
        "o": "Galerie Sievi",
        "d": [
          "2010-05-08",
          "2010-06-26"
        ]
      }
    ],
    "2008": [
      {
        "i": "9610-651-2008-02-15",
        "c": "DE",
        "n": "Jean- François Chaussepied - \"La Mémoire des Vents\"",
        "t": "Galerie privée",
        "st": "Solo",
        "ct": "Berlin",
        "o": "Galerie Sievi",
        "d": [
          "2008-02-15",
          "2008-04-12"
        ]
      }
    ],
    "2011": [
      {
        "i": "9610-651-2011-05-07",
        "c": "DE",
        "n": "Les couleurs du Silence",
        "t": "Galerie privée",
        "st": "Solo",
        "ct": "Berlin",
        "o": "Galerie Sievi",
        "d": [
          "2011-05-07",
          "2011-07-02"
        ]
      }
    ]
  }
}