{
  "id": "23221",
  "name": "Galerie Artraces",
  "street": "12/14 rue Georges Huchon",
  "zip": "94300",
  "city": "Vincennes",
  "country": "France",
  "foundation": null,
  "directeurs": "",
  "profile": null,
  "tel": "+33 (0) 950 558 306",
  "email": "contact@artraces.fr",
  "www": "www.artraces.fr",
  "map": "http://maps.google.com/maps?q=Vincennes%2C%2094300 %2C%20 %2C%2012/14 rue Georges Huchon %2C%20France",
  "fairs-total": "1",
  "fairs-abroad": "0",
  "fairs-in-FR": "1",
  "fairs": {
    "2010": [
      {
        "i": "23221-cutlog 2010",
        "c": "FR"
      }
    ]
  }
}